DevDrip-0.0.1.dist-info/METADATA
DevDrip-0.0.1.dist-info/RECORD
DevDrip-0.0.1.dist-info/WHEEL
DevDrip-0.0.1.dist-info/top_level.txt
devdrip/__init__.py
devdrip/client.py
