Metadata-Version: 2.1
Name: DevDrip
Version: 0.0.1
Summary: DevDrip client
Home-page: https://www.wabisabiventures.com
Author: Alex Roe
Author-email: alex@wabisabiventures.com
License: UNKNOWN
Platform: UNKNOWN
